vsmmath/__init__.py
vsmmath/add.py
vsmmath/subtract.py
vsmmath/extras/__init__.py
vsmmath/extras/divide.py
vsmmath/extras/multiply.py
vsmmath-0.0.1.dist-info/METADATA
vsmmath-0.0.1.dist-info/WHEEL
vsmmath-0.0.1.dist-info/top_level.txt
vsmmath-0.0.1.dist-info/RECORD
